zimo_web_screenshot/__init__.py
zimo_web_screenshot/screenshot.py
zimo_web_screenshot-0.4.1.dist-info/LICENSE
zimo_web_screenshot-0.4.1.dist-info/METADATA
zimo_web_screenshot-0.4.1.dist-info/WHEEL
zimo_web_screenshot-0.4.1.dist-info/entry_points.txt
zimo_web_screenshot-0.4.1.dist-info/top_level.txt
zimo_web_screenshot-0.4.1.dist-info/RECORD
