Metadata-Version: 2.1
Name: zimo-web-screenshot
Version: 0.4.1
Summary: A simple CLI tool to take screenshots of Zimo Web pages with Selenium.
Home-page: https://github.com/zimoluo/zimo-web-screenshot-tool
Author: Zimo Luo
Author-email: abgkings0920@gmail.com
License: MIT
Classifier: Programming Language :: Python :: 3
Classifier: License :: OSI Approved :: MIT License
Classifier: Operating System :: OS Independent
Requires-Python: >=3.6
License-File: LICENSE
Requires-Dist: selenium
